dwopt/__init__.py
dwopt/_qry.py
dwopt/dbo.py
dwopt/set_up.py
dwopt/testing.py
dwopt-0.0.9.dist-info/LICENSE
dwopt-0.0.9.dist-info/METADATA
dwopt-0.0.9.dist-info/WHEEL
dwopt-0.0.9.dist-info/top_level.txt
dwopt-0.0.9.dist-info/RECORD
