Metadata-Version: 2.1
Name: dwopt
Version: 0.0.9
Summary: SQL query abstraction library
Home-page: https://github.com/0xdomyz/dwopt
Author: 0xdomyz
Author-email: septemberwhyms@gmail.com
Project-URL: Bug Tracker, https://github.com/0xdomyz/dwopt/issues
Classifier: Programming Language :: Python :: 3.10
Classifier: Programming Language :: Python :: 3.11
Classifier: License :: OSI Approved :: MIT License
Classifier: Operating System :: Microsoft :: Windows :: Windows 10
Classifier: Operating System :: POSIX :: Linux
License-File: LICENSE
Requires-Dist: sqlalchemy
Requires-Dist: pandas
Requires-Dist: keyring
Requires-Dist: keyrings.alt
